tevildo/cli.py
tevildo/completer.py
tevildo-2024.12.10.74246.dist-info/METADATA
tevildo-2024.12.10.74246.dist-info/WHEEL
tevildo-2024.12.10.74246.dist-info/entry_points.txt
tevildo-2024.12.10.74246.dist-info/RECORD
