Metadata-Version: 2.1
Name: tevildo
Version: 2024.12.10.74246
Summary: A python based OpenAI bot for shell environments
License: MIT
Author: Amarpreet Singh
Author-email: solamarpreet@gmail.com
Requires-Python: >=3.10,<4.0
Classifier: License :: OSI Approved :: MIT License
Classifier: Programming Language :: Python :: 3
Classifier: Programming Language :: Python :: 3.10
Classifier: Programming Language :: Python :: 3.11
Classifier: Programming Language :: Python :: 3.12
Classifier: Programming Language :: Python :: 3.13
Requires-Dist: openai (>=1.3.7,<2.0.0)
Requires-Dist: prompt-toolkit (>=3.0.41,<4.0.0)
Requires-Dist: python-dotenv (>=1.0.0,<2.0.0)
